kent/__init__.py
kent/app.py
kent/cli_server.py
kent/cli_testpost.py
kent/utils.py
kent/static/favicon.ico
kent/static/pico.1.5.3.min.css
kent/static/pico_LICENSE.md
kent/static/style.css
kent/templates/index.html
kent-2.2.0.dist-info/licenses/LICENSE
kent-2.2.0.dist-info/METADATA
kent-2.2.0.dist-info/WHEEL
kent-2.2.0.dist-info/entry_points.txt
kent-2.2.0.dist-info/top_level.txt
kent-2.2.0.dist-info/RECORD
