Metadata-Version: 2.4
Name: kent
Version: 2.2.0
Summary: Fake Sentry service for debugging and integration tests
Author: Will Kahn-Greene
License: MPLv2
Project-URL: Homepage, https://github.com/mozilla-services/kent/
Project-URL: Source, https://github.com/mozilla-services/kent/
Project-URL: Issues, https://github.com/mozilla-services/kent/issues
Keywords: sentry,integration service,test
Classifier: Development Status :: 5 - Production/Stable
Classifier: Intended Audience :: Developers
Classifier: License :: OSI Approved :: Mozilla Public License 2.0 (MPL 2.0)
Classifier: Natural Language :: English
Classifier: Programming Language :: Python :: 3 :: Only
Classifier: Programming Language :: Python :: 3.10
Classifier: Programming Language :: Python :: 3.11
Classifier: Programming Language :: Python :: 3.12
Classifier: Programming Language :: Python :: 3.13
Classifier: Programming Language :: Python :: 3.14
Requires-Python: >=3.10
License-File: LICENSE
Requires-Dist: flask>3
Provides-Extra: dev
Requires-Dist: build; extra == "dev"
Requires-Dist: pytest; extra == "dev"
Requires-Dist: requests; extra == "dev"
Requires-Dist: ruff; extra == "dev"
Requires-Dist: sentry-sdk; extra == "dev"
Requires-Dist: setuptools; extra == "dev"
Requires-Dist: tox; extra == "dev"
Requires-Dist: tox-gh-actions; extra == "dev"
Requires-Dist: tox-uv; extra == "dev"
Requires-Dist: twine; extra == "dev"
Dynamic: license-file
